fandockermcp/__init__.py
fandockermcp-0.1.1.dist-info/METADATA
fandockermcp-0.1.1.dist-info/WHEEL
fandockermcp-0.1.1.dist-info/entry_points.txt
fandockermcp-0.1.1.dist-info/RECORD
