Metadata-Version: 2.4
Name: fandockermcp
Version: 0.1.1
Summary: 这是一个使用FastMCP框架构建的Docker镜像管理工具，可以方便地拉取和管理Docker镜像。
Author-email: root <qq91349532@163.com>
Requires-Python: >=3.13
Requires-Dist: mcp[cli]>=1.14.1
